{"id":"f5ac6879-1ffe-470c-ba81-34a3e3af8ee8","createTime":1648923477792137,"modifiedTime":1655203854454040,"enableUpload":true,"author":"张益达","postScript":"","name":"555电影","host":"https://www.5dy5.vip","group":"","contentType":2,"sort":10490,"useCryptoJS":false,"loadJs":"","userAgent":"","enableDiscover":true,"discoverUrl":"@js:\n(() => {\r\n    let url = '';\r\n    if (params.tabIndex == 0) {\r\n        url = host + '/vodshow/'+params.filters.cat+'-' +\r\n            params.filters.area + '-' +\r\n            params.filters.sort + '-' +\r\n            params.filters.type + '-----' +\r\n            params.pageIndex + '---' +\r\n            params.filters.year + '.html';\r\n    } else if (params.tabIndex == 1) {\r\n        url = host + '/vodshow/1-' +\r\n            params.filters.area + '-' +\r\n            params.filters.sort + '-' +\r\n            params.filters.type + '-' +\r\n            params.filters.lang + '----' +\r\n            params.pageIndex + '---' +\r\n            params.filters.year + '.html';\r\n    } else if (params.tabIndex == 2) {\r\n        url = host + '/vodshow/4-' +\r\n            params.filters.area + '-' +\r\n            params.filters.sort + '-' +\r\n            params.filters.type + '-' +\r\n            params.filters.lang + '----' +\r\n            params.pageIndex + '---' +\r\n            params.filters.year + '.html';\r\n    } else if (params.tabIndex == 3) {\r\n        url = host + '/vodshow/3-' +\r\n            params.filters.area + '-' +\r\n            params.filters.sort + '-' +\r\n            params.filters.type + '-' +\r\n            params.filters.lang + '----' +\r\n            params.pageIndex + '---' +\r\n            params.filters.year + '.html';\r\n    } else if (params.tabIndex == 4) {\r\n        url = host + '/label/netflix/page/' + params.pageIndex + '.html';\r\n    } else if (params.tabIndex == 5) {\r\n        url = host + '/vodshow/124--' + params.filters.sort + '------' + params.pageIndex + '---' + '.html';\r\n    }\r\n    return {\r\n        'url': url,\r\n    };\r\n})()","discoverMoreKeys":"{\"list\":[{\"title\":\"连续剧\",\"requestFilters\":[{\"items\":[{\"title\":\"全部\",\"value\":\"2\"},{\"title\":\"热门连续剧\",\"value\":\"13\"},{\"title\":\"港台剧\",\"value\":\"15\"},{\"title\":\"日韩剧\",\"value\":\"44\"},{\"title\":\"欧美剧\",\"value\":\"45\"}],\"key\":\"cat\",\"value\":\"2\"},{\"items\":[{\"title\":\"全部\",\"value\":\"\"},{\"title\":\"Netflix\",\"value\":\"Netflix\"},{\"title\":\"剧情\",\"value\":\"%E5%89%A7%E6%83%85\"},{\"title\":\"丧尸\",\"value\":\"%E4%B8%A7%E5%B0%B8\"},{\"title\":\"仙侠\",\"value\":\"%E4%BB%99%E4%BE%A0\"},{\"title\":\"穿越\",\"value\":\"%E7%A9%BF%E8%B6%8A\"},{\"title\":\"惊悚\",\"value\":\"%E6%83%8A%E6%82%9A\"},{\"title\":\"恐怖\",\"value\":\"%E6%81%90%E6%80%96\"},{\"title\":\"言情\",\"value\":\"%E8%A8%80%E6%83%85\"},{\"title\":\"科幻\",\"value\":\"%E7%A7%91%E5%B9%BB\"},{\"title\":\"动作\",\"value\":\"%E5%8A%A8%E4%BD%9C\"},{\"title\":\"喜剧\",\"value\":\"%E5%96%9C%E5%89%A7\"},{\"title\":\"爱情\",\"value\":\"%E7%88%B1%E6%83%85\"},{\"title\":\"偶像\",\"value\":\"%E5%81%B6%E5%83%8F\"},{\"title\":\"都市\",\"value\":\"%E9%83%BD%E5%B8%82\"},{\"title\":\"军旅\",\"value\":\"%E5%86%9B%E6%97%85\"},{\"title\":\"谍战\",\"value\":\"%E8%B0%8D%E6%88%98\"},{\"title\":\"罪案\",\"value\":\"%E7%BD%AA%E6%A1%88\"},{\"title\":\"宫廷\",\"value\":\"%E5%AE%AB%E5%BB%B7\"},{\"title\":\"冒险\",\"value\":\"%E5%86%92%E9%99%A9\"},{\"title\":\"儿童\",\"value\":\"%E5%84%BF%E7%AB%A5\"},{\"title\":\"歌舞\",\"value\":\"%E6%AD%8C%E8%88%9E\"},{\"title\":\"音乐\",\"value\":\"%E9%9F%B3%E4%B9%90\"},{\"title\":\"奇幻\",\"value\":\"%E5%A5%87%E5%B9%BB\"},{\"title\":\"动画\",\"value\":\"%E5%8A%A8%E7%94%BB\"},{\"title\":\"战争\",\"value\":\"%E6%88%98%E4%BA%89\"},{\"title\":\"传记\",\"value\":\"%E4%BC%A0%E8%AE%B0\"},{\"title\":\"记录\",\"value\":\"%E8%AE%B0%E5%BD%95\"},{\"title\":\"犯罪\",\"value\":\"%E7%8A%AF%E7%BD%AA\"},{\"title\":\"悬疑\",\"value\":\"%E6%82%AC%E7%96%91\"},{\"title\":\"西部\",\"value\":\"%E8%A5%BF%E9%83%A8\"},{\"title\":\"灾难\",\"value\":\"%E7%81%BE%E9%9A%BE\"},{\"title\":\"古装\",\"value\":\"%E5%8F%A4%E8%A3%85\"},{\"title\":\"武侠\",\"value\":\"%E6%AD%A6%E4%BE%A0\"},{\"title\":\"家庭\",\"value\":\"%E5%AE%B6%E5%BA%AD\"},{\"title\":\"短片\",\"value\":\"%E7%9F%AD%E7%89%87\"},{\"title\":\"校园\",\"value\":\"%E6%A0%A1%E5%9B%AD\"},{\"title\":\"文艺\",\"value\":\"%E6%96%87%E8%89%BA\"},{\"title\":\"运动\",\"value\":\"%E8%BF%90%E5%8A%A8\"},{\"title\":\"青春\",\"value\":\"%E9%9D%92%E6%98%A5\"},{\"title\":\"同性\",\"value\":\"%E5%90%8C%E6%80%A7\"},{\"title\":\"励志\",\"value\":\"%E5%8A%B1%E5%BF%97\"},{\"title\":\"人性\",\"value\":\"%E4%BA%BA%E6%80%A7\"},{\"title\":\"美食\",\"value\":\"%E7%BE%8E%E9%A3%9F\"},{\"title\":\"女性\",\"value\":\"%E5%A5%B3%E6%80%A7\"},{\"title\":\"治愈\",\"value\":\"%E6%B2%BB%E6%84%88\"},{\"title\":\"历史\",\"value\":\"%E5%8E%86%E5%8F%B2\"},{\"title\":\"真人秀\",\"value\":\"%E7%9C%9F%E4%BA%BA%E7%A7%80\"},{\"title\":\"脱口秀\",\"value\":\"%E8%84%B1%E5%8F%A3%E7%A7%80\"}],\"key\":\"type\",\"value\":\"\"},{\"items\":[{\"title\":\"全部\",\"value\":\"\"},{\"title\":\"大陆\",\"value\":\"%E5%A4%A7%E9%99%86\"},{\"title\":\"香港\",\"value\":\"%E9%A6%99%E6%B8%AF\"},{\"title\":\"韩国\",\"value\":\"%E9%9F%A9%E5%9B%BD\"},{\"title\":\"美国\",\"value\":\"%E7%BE%8E%E5%9B%BD\"},{\"title\":\"日本\",\"value\":\"%E6%97%A5%E6%9C%AC\"},{\"title\":\"法国\",\"value\":\"%E6%B3%95%E5%9B%BD\"},{\"title\":\"英国\",\"value\":\"%E8%8B%B1%E5%9B%BD\"},{\"title\":\"德国\",\"value\":\"%E5%BE%B7%E5%9B%BD\"},{\"title\":\"台湾\",\"value\":\"%E5%8F%B0%E6%B9%BE\"},{\"title\":\"泰国\",\"value\":\"%E6%B3%B0%E5%9B%BD\"},{\"title\":\"印度\",\"value\":\"%E5%8D%B0%E5%BA%A6\"},{\"title\":\"其他\",\"value\":\"%E5%85%B6%E4%BB%96\"}],\"key\":\"area\",\"value\":\"\"},{\"items\":[{\"title\":\"全部\",\"value\":\"\"},{\"title\":\"2022\",\"value\":\"2022\"},{\"title\":\"2021\",\"value\":\"2021\"},{\"title\":\"2020\",\"value\":\"2020\"},{\"title\":\"2019\",\"value\":\"2019\"},{\"title\":\"2018\",\"value\":\"2018\"},{\"title\":\"2017\",\"value\":\"2017\"},{\"title\":\"2016\",\"value\":\"2016\"},{\"title\":\"2015\",\"value\":\"2015\"},{\"title\":\"2014\",\"value\":\"2014\"},{\"title\":\"2013\",\"value\":\"2013\"},{\"title\":\"2012\",\"value\":\"2012\"},{\"title\":\"2011\",\"value\":\"2011\"},{\"title\":\"2010\",\"value\":\"2010\"},{\"title\":\"2009\",\"value\":\"2009\"},{\"title\":\"2008\",\"value\":\"2008\"},{\"title\":\"2007\",\"value\":\"2007\"}],\"key\":\"year\",\"value\":\"\"},{\"items\":[{\"title\":\"全部\",\"value\":\"\"},{\"title\":\"时间\",\"value\":\"time\"},{\"title\":\"人气\",\"value\":\"hits\"},{\"title\":\"评分\",\"value\":\"score\"}],\"key\":\"sort\",\"value\":\"\"}]},{\"title\":\"电影\",\"requestFilters\":[{\"items\":[{\"title\":\"全部\",\"value\":\"\"},{\"title\":\"Netflix\",\"value\":\"Netflix\"},{\"title\":\"仙侠\",\"value\":\"%E4%BB%99%E4%BE%A0\"},{\"title\":\"剧情\",\"value\":\"%E5%89%A7%E6%83%85\"},{\"title\":\"科幻\",\"value\":\"%E7%A7%91%E5%B9%BB\"},{\"title\":\"动作\",\"value\":\"%E5%8A%A8%E4%BD%9C\"},{\"title\":\"喜剧\",\"value\":\"%E5%96%9C%E5%89%A7\"},{\"title\":\"爱情\",\"value\":\"%E7%88%B1%E6%83%85\"},{\"title\":\"冒险\",\"value\":\"%E5%86%92%E9%99%A9\"},{\"title\":\"儿童\",\"value\":\"%E5%84%BF%E7%AB%A5\"},{\"title\":\"歌舞\",\"value\":\"%E6%AD%8C%E8%88%9E\"},{\"title\":\"音乐\",\"value\":\"%E9%9F%B3%E4%B9%90\"},{\"title\":\"奇幻\",\"value\":\"%E5%A5%87%E5%B9%BB\"},{\"title\":\"动画\",\"value\":\"%E5%8A%A8%E7%94%BB\"},{\"title\":\"恐怖\",\"value\":\"%E6%81%90%E6%80%96\"},{\"title\":\"惊悚\",\"value\":\"%E6%83%8A%E6%82%9A\"},{\"title\":\"丧尸\",\"value\":\"%E4%B8%A7%E5%B0%B8\"},{\"title\":\"战争\",\"value\":\"%E6%88%98%E4%BA%89\"},{\"title\":\"传记\",\"value\":\"%E4%BC%A0%E8%AE%B0\"},{\"title\":\"纪录\",\"value\":\"%E7%BA%AA%E5%BD%95\"},{\"title\":\"犯罪\",\"value\":\"%E7%8A%AF%E7%BD%AA\"},{\"title\":\"悬疑\",\"value\":\"%E6%82%AC%E7%96%91\"},{\"title\":\"西部\",\"value\":\"%E8%A5%BF%E9%83%A8\"},{\"title\":\"灾难\",\"value\":\"%E7%81%BE%E9%9A%BE\"},{\"title\":\"古装\",\"value\":\"%E5%8F%A4%E8%A3%85\"},{\"title\":\"武侠\",\"value\":\"%E6%AD%A6%E4%BE%A0\"},{\"title\":\"家庭\",\"value\":\"%E5%AE%B6%E5%BA%AD\"},{\"title\":\"短片\",\"value\":\"%E7%9F%AD%E7%89%87\"},{\"title\":\"校园\",\"value\":\"%E6%A0%A1%E5%9B%AD\"},{\"title\":\"文艺\",\"value\":\"%E6%96%87%E8%89%BA\"},{\"title\":\"运动\",\"value\":\"%E8%BF%90%E5%8A%A8\"},{\"title\":\"青春\",\"value\":\"%E9%9D%92%E6%98%A5\"},{\"title\":\"同性\",\"value\":\"%E5%90%8C%E6%80%A7\"},{\"title\":\"励志\",\"value\":\"%E5%8A%B1%E5%BF%97\"},{\"title\":\"人性\",\"value\":\"%E4%BA%BA%E6%80%A7\"},{\"title\":\"美食\",\"value\":\"%E7%BE%8E%E9%A3%9F\"},{\"title\":\"女性\",\"value\":\"%E5%A5%B3%E6%80%A7\"},{\"title\":\"治愈\",\"value\":\"%E6%B2%BB%E6%84%88\"},{\"title\":\"历史\",\"value\":\"%E5%8E%86%E5%8F%B2\"},{\"title\":\"真人秀\",\"value\":\"%E7%9C%9F%E4%BA%BA%E7%A7%80\"},{\"title\":\"脱口秀\",\"value\":\"%E8%84%B1%E5%8F%A3%E7%A7%80\"}],\"key\":\"type\",\"value\":\"\"},{\"items\":[{\"title\":\"全部\",\"value\":\"\"},{\"title\":\"大陆\",\"value\":\"%E5%A4%A7%E9%99%86\"},{\"title\":\"香港\",\"value\":\"%E9%A6%99%E6%B8%AF\"},{\"title\":\"台湾\",\"value\":\"%E5%8F%B0%E6%B9%BE\"},{\"title\":\"美国\",\"value\":\"%E7%BE%8E%E5%9B%BD\"},{\"title\":\"日本\",\"value\":\"%E6%97%A5%E6%9C%AC\"},{\"title\":\"韩国\",\"value\":\"%E9%9F%A9%E5%9B%BD\"},{\"title\":\"英国\",\"value\":\"%E8%8B%B1%E5%9B%BD\"},{\"title\":\"法国\",\"value\":\"%E6%B3%95%E5%9B%BD\"},{\"title\":\"德国\",\"value\":\"%E5%BE%B7%E5%9B%BD\"},{\"title\":\"印度\",\"value\":\"%E5%8D%B0%E5%BA%A6\"},{\"title\":\"泰国\",\"value\":\"%E6%B3%B0%E5%9B%BD\"},{\"title\":\"丹麦\",\"value\":\"%E4%B8%B9%E9%BA%A6\"},{\"title\":\"瑞典\",\"value\":\"%E7%91%9E%E5%85%B8\"},{\"title\":\"巴西\",\"value\":\"%E5%B7%B4%E8%A5%BF\"},{\"title\":\"加拿大\",\"value\":\"%E5%8A%A0%E6%8B%BF%E5%A4%A7\"},{\"title\":\"俄罗斯\",\"value\":\"%E4%BF%84%E7%BD%97%E6%96%AF\"},{\"title\":\"意大利\",\"value\":\"%E6%84%8F%E5%A4%A7%E5%88%A9\"},{\"title\":\"比利时\",\"value\":\"%E6%AF%94%E5%88%A9%E6%97%B6\"},{\"title\":\"爱尔兰\",\"value\":\"%E7%88%B1%E5%B0%94%E5%85%B0\"},{\"title\":\"西班牙\",\"value\":\"%E8%A5%BF%E7%8F%AD%E7%89%99\"},{\"title\":\"澳大利亚\",\"value\":\"%E6%BE%B3%E5%A4%A7%E5%88%A9%E4%BA%9A\"}],\"key\":\"area\",\"value\":\"\"},{\"items\":[{\"title\":\"全部\",\"value\":\"\"},{\"title\":\"英语\",\"value\":\"%E8%8B%B1%E8%AF%AD\"},{\"title\":\"法语\",\"value\":\"%E6%B3%95%E8%AF%AD\"},{\"title\":\"国语\",\"value\":\"%E5%9B%BD%E8%AF%AD\"},{\"title\":\"粤语\",\"value\":\"%E7%B2%A4%E8%AF%AD\"},{\"title\":\"日语\",\"value\":\"%E6%97%A5%E8%AF%AD\"},{\"title\":\"韩语\",\"value\":\"%E9%9F%A9%E8%AF%AD\"},{\"title\":\"泰语\",\"value\":\"%E6%B3%B0%E8%AF%AD\"},{\"title\":\"德语\",\"value\":\"%E5%BE%B7%E8%AF%AD\"},{\"title\":\"俄语\",\"value\":\"%E4%BF%84%E8%AF%AD\"},{\"title\":\"闽南语\",\"value\":\"%E9%97%BD%E5%8D%97%E8%AF%AD\"},{\"title\":\"丹麦语\",\"value\":\"%E4%B8%B9%E9%BA%A6%E8%AF%AD\"},{\"title\":\"波兰语\",\"value\":\"%E6%B3%A2%E5%85%B0%E8%AF%AD\"},{\"title\":\"瑞典语\",\"value\":\"%E7%91%9E%E5%85%B8%E8%AF%AD\"},{\"title\":\"印地语\",\"value\":\"%E5%8D%B0%E5%9C%B0%E8%AF%AD\"},{\"title\":\"挪威语\",\"value\":\"%E6%8C%AA%E5%A8%81%E8%AF%AD\"},{\"title\":\"意大利语\",\"value\":\"%E6%84%8F%E5%A4%A7%E5%88%A9%E8%AF%AD\"},{\"title\":\"西班牙语\",\"value\":\"%E8%A5%BF%E7%8F%AD%E7%89%99%E8%AF%AD\"}],\"key\":\"lang\",\"value\":\"\"},{\"items\":[{\"title\":\"全部\",\"value\":\"\"},{\"title\":\"2022\",\"value\":\"2022\"},{\"title\":\"2021\",\"value\":\"2021\"},{\"title\":\"2020\",\"value\":\"2020\"},{\"title\":\"2019\",\"value\":\"2019\"},{\"title\":\"2018\",\"value\":\"2018\"},{\"title\":\"2017\",\"value\":\"2017\"},{\"title\":\"2016\",\"value\":\"2016\"},{\"title\":\"2015\",\"value\":\"2015\"},{\"title\":\"2014\",\"value\":\"2014\"},{\"title\":\"2013\",\"value\":\"2013\"},{\"title\":\"2012\",\"value\":\"2012\"},{\"title\":\"2011\",\"value\":\"2011\"},{\"title\":\"2010\",\"value\":\"2010\"},{\"title\":\"2009\",\"value\":\"2009\"},{\"title\":\"2008\",\"value\":\"2008\"},{\"title\":\"2007\",\"value\":\"2007\"}],\"key\":\"year\",\"value\":\"\"},{\"items\":[{\"title\":\"全部\",\"value\":\"\"},{\"title\":\"时间\",\"value\":\"time\"},{\"title\":\"人气\",\"value\":\"hits\"},{\"title\":\"评分\",\"value\":\"score\"}],\"key\":\"sort\",\"value\":\"\"}]},{\"title\":\"动漫\",\"requestFilters\":[{\"items\":[{\"title\":\"全部\",\"value\":\"\"},{\"title\":\"Netflix\",\"value\":\"Netflix\"},{\"title\":\"热血\",\"value\":\"%E7%83%AD%E8%A1%80\"},{\"title\":\"科幻\",\"value\":\"%E7%A7%91%E5%B9%BB\"},{\"title\":\"美少女\",\"value\":\"%E7%BE%8E%E5%B0%91%E5%A5%B3\"},{\"title\":\"魔幻\",\"value\":\"%E9%AD%94%E5%B9%BB\"},{\"title\":\"经典\",\"value\":\"%E7%BB%8F%E5%85%B8\"},{\"title\":\"励志\",\"value\":\"%E5%8A%B1%E5%BF%97\"},{\"title\":\"少儿\",\"value\":\"%E5%B0%91%E5%84%BF\"},{\"title\":\"冒险\",\"value\":\"%E5%86%92%E9%99%A9\"},{\"title\":\"搞笑\",\"value\":\"%E6%90%9E%E7%AC%91\"},{\"title\":\"推理\",\"value\":\"%E6%8E%A8%E7%90%86\"},{\"title\":\"恋爱\",\"value\":\"%E6%81%8B%E7%88%B1\"},{\"title\":\"治愈\",\"value\":\"%E6%B2%BB%E6%84%88\"},{\"title\":\"幻想\",\"value\":\"%E5%B9%BB%E6%83%B3\"},{\"title\":\"校园\",\"value\":\"%E6%A0%A1%E5%9B%AD\"},{\"title\":\"动物\",\"value\":\"%E5%8A%A8%E7%89%A9\"},{\"title\":\"机战\",\"value\":\"%E6%9C%BA%E6%88%98\"},{\"title\":\"亲子\",\"value\":\"%E4%BA%B2%E5%AD%90\"},{\"title\":\"儿歌\",\"value\":\"%E5%84%BF%E6%AD%8C\"},{\"title\":\"运动\",\"value\":\"%E8%BF%90%E5%8A%A8\"},{\"title\":\"悬疑\",\"value\":\"%E6%82%AC%E7%96%91\"},{\"title\":\"怪物\",\"value\":\"%E6%80%AA%E7%89%A9\"},{\"title\":\"战争\",\"value\":\"%E6%88%98%E4%BA%89\"},{\"title\":\"益智\",\"value\":\"%E7%9B%8A%E6%99%BA\"},{\"title\":\"青春\",\"value\":\"%E9%9D%92%E6%98%A5\"},{\"title\":\"童话\",\"value\":\"%E7%AB%A5%E8%AF%9D\"},{\"title\":\"竞技\",\"value\":\"%E7%AB%9E%E6%8A%80\"},{\"title\":\"动作\",\"value\":\"%E5%8A%A8%E4%BD%9C\"},{\"title\":\"社会\",\"value\":\"%E7%A4%BE%E4%BC%9A\"},{\"title\":\"友情\",\"value\":\"%E5%8F%8B%E6%83%85\"},{\"title\":\"真人版\",\"value\":\"%E7%9C%9F%E4%BA%BA%E7%89%88\"},{\"title\":\"电影版\",\"value\":\"%E7%94%B5%E5%BD%B1%E7%89%88\"},{\"title\":\"OVA版\",\"value\":\"OVA%E7%89%88\"},{\"title\":\"TV版\",\"value\":\"TV%E7%89%88\"},{\"title\":\"新番动画\",\"value\":\"%E6%96%B0%E7%95%AA%E5%8A%A8%E7%94%BB\"},{\"title\":\"完结动画\",\"value\":\"%E5%AE%8C%E7%BB%93%E5%8A%A8%E7%94%BB\"}],\"key\":\"type\",\"value\":\"\"},{\"items\":[{\"title\":\"全部\",\"value\":\"\"},{\"title\":\"大陆\",\"value\":\"%E5%A4%A7%E9%99%86\"},{\"title\":\"日本\",\"value\":\"%E6%97%A5%E6%9C%AC\"},{\"title\":\"欧美\",\"value\":\"%E6%AC%A7%E7%BE%8E\"},{\"title\":\"其他\",\"value\":\"%E5%85%B6%E4%BB%96\"}],\"key\":\"area\",\"value\":\"\"},{\"items\":[{\"title\":\"全部\",\"value\":\"\"},{\"title\":\"国语\",\"value\":\"%E5%9B%BD%E8%AF%AD\"},{\"title\":\"英语\",\"value\":\"%E8%8B%B1%E8%AF%AD\"},{\"title\":\"粤语\",\"value\":\"%E7%B2%A4%E8%AF%AD\"},{\"title\":\"闽南语\",\"value\":\"%E9%97%BD%E5%8D%97%E8%AF%AD\"},{\"title\":\"韩语\",\"value\":\"%E9%9F%A9%E8%AF%AD\"},{\"title\":\"日语\",\"value\":\"%E6%97%A5%E8%AF%AD\"},{\"title\":\"其它\",\"value\":\"%E5%85%B6%E5%AE%83\"}],\"key\":\"lang\",\"value\":\"\"},{\"items\":[{\"title\":\"全部\",\"value\":\"\"},{\"title\":\"2022\",\"value\":\"2022\"},{\"title\":\"2021\",\"value\":\"2021\"},{\"title\":\"2020\",\"value\":\"2020\"},{\"title\":\"2019\",\"value\":\"2019\"},{\"title\":\"2018\",\"value\":\"2018\"},{\"title\":\"2017\",\"value\":\"2017\"},{\"title\":\"2016\",\"value\":\"2016\"},{\"title\":\"2015\",\"value\":\"2015\"},{\"title\":\"2014\",\"value\":\"2014\"},{\"title\":\"2013\",\"value\":\"2013\"},{\"title\":\"2012\",\"value\":\"2012\"},{\"title\":\"2011\",\"value\":\"2011\"},{\"title\":\"2010\",\"value\":\"2010\"},{\"title\":\"2009\",\"value\":\"2009\"},{\"title\":\"2008\",\"value\":\"2008\"},{\"title\":\"2007\",\"value\":\"2007\"},{\"title\":\"2006\",\"value\":\"2006\"},{\"title\":\"2005\",\"value\":\"2005\"},{\"title\":\"2004\",\"value\":\"2004\"},{\"title\":\"更早\",\"value\":\"%E6%9B%B4%E6%97%A9\"}],\"key\":\"year\",\"value\":\"\"},{\"items\":[{\"title\":\"全部\",\"value\":\"\"},{\"title\":\"时间\",\"value\":\"time\"},{\"title\":\"人气\",\"value\":\"hits\"},{\"title\":\"评分\",\"value\":\"score\"}],\"key\":\"sort\",\"value\":\"\"}]},{\"title\":\"综艺记录\",\"requestFilters\":[{\"items\":[{\"title\":\"全部\",\"value\":\"\"},{\"title\":\"YouTube\",\"value\":\"YouTube\"},{\"title\":\"脱口秀\",\"value\":\"%E8%84%B1%E5%8F%A3%E7%A7%80\"},{\"title\":\"真人秀\",\"value\":\"%E7%9C%9F%E4%BA%BA%E7%A7%80\"},{\"title\":\"选秀\",\"value\":\"%E9%80%89%E7%A7%80\"},{\"title\":\"八卦\",\"value\":\"%E5%85%AB%E5%8D%A6\"},{\"title\":\"访谈\",\"value\":\"%E8%AE%BF%E8%B0%88\"},{\"title\":\"情感\",\"value\":\"%E6%83%85%E6%84%9F\"},{\"title\":\"生活\",\"value\":\"%E7%94%9F%E6%B4%BB\"},{\"title\":\"晚会\",\"value\":\"%E6%99%9A%E4%BC%9A\"},{\"title\":\"搞笑\",\"value\":\"%E6%90%9E%E7%AC%91\"},{\"title\":\"音乐\",\"value\":\"%E9%9F%B3%E4%B9%90\"},{\"title\":\"时尚\",\"value\":\"%E6%97%B6%E5%B0%9A\"},{\"title\":\"游戏\",\"value\":\"%E6%B8%B8%E6%88%8F\"},{\"title\":\"少儿\",\"value\":\"%E5%B0%91%E5%84%BF\"},{\"title\":\"体育\",\"value\":\"%E4%BD%93%E8%82%B2\"},{\"title\":\"纪实\",\"value\":\"%E7%BA%AA%E5%AE%9E\"},{\"title\":\"科教\",\"value\":\"%E7%A7%91%E6%95%99\"},{\"title\":\"曲艺\",\"value\":\"%E6%9B%B2%E8%89%BA\"},{\"title\":\"歌舞\",\"value\":\"%E6%AD%8C%E8%88%9E\"},{\"title\":\"财经\",\"value\":\"%E8%B4%A2%E7%BB%8F\"},{\"title\":\"汽车\",\"value\":\"%E6%B1%BD%E8%BD%A6\"},{\"title\":\"播报\",\"value\":\"%E6%92%AD%E6%8A%A5\"},{\"title\":\"其他\",\"value\":\"%E5%85%B6%E4%BB%96\"}],\"key\":\"type\",\"value\":\"\"},{\"items\":[{\"title\":\"全部\",\"value\":\"\"},{\"title\":\"大陆\",\"value\":\"%E5%A4%A7%E9%99%86\"},{\"title\":\"韩国\",\"value\":\"%E9%9F%A9%E5%9B%BD\"},{\"title\":\"香港\",\"value\":\"%E9%A6%99%E6%B8%AF\"},{\"title\":\"台湾\",\"value\":\"%E5%8F%B0%E6%B9%BE\"},{\"title\":\"美国\",\"value\":\"%E7%BE%8E%E5%9B%BD\"},{\"title\":\"其它\",\"value\":\"%E5%85%B6%E5%AE%83\"}],\"key\":\"area\",\"value\":\"\"},{\"items\":[{\"title\":\"全部\",\"value\":\"\"},{\"title\":\"国语\",\"value\":\"%E5%9B%BD%E8%AF%AD\"},{\"title\":\"英语\",\"value\":\"%E8%8B%B1%E8%AF%AD\"},{\"title\":\"粤语\",\"value\":\"%E7%B2%A4%E8%AF%AD\"},{\"title\":\"闽南语\",\"value\":\"%E9%97%BD%E5%8D%97%E8%AF%AD\"},{\"title\":\"韩语\",\"value\":\"%E9%9F%A9%E8%AF%AD\"},{\"title\":\"日语\",\"value\":\"%E6%97%A5%E8%AF%AD\"},{\"title\":\"其它\",\"value\":\"%E5%85%B6%E5%AE%83\"}],\"key\":\"lang\",\"value\":\"\"},{\"items\":[{\"title\":\"全部\",\"value\":\"\"},{\"title\":\"2022\",\"value\":\"2022\"},{\"title\":\"2021\",\"value\":\"2021\"},{\"title\":\"2020\",\"value\":\"2020\"},{\"title\":\"2019\",\"value\":\"2019\"},{\"title\":\"2018\",\"value\":\"2018\"},{\"title\":\"2017\",\"value\":\"2017\"},{\"title\":\"2016\",\"value\":\"2016\"},{\"title\":\"2015\",\"value\":\"2015\"},{\"title\":\"2014\",\"value\":\"2014\"},{\"title\":\"2013\",\"value\":\"2013\"},{\"title\":\"2012\",\"value\":\"2012\"},{\"title\":\"2011\",\"value\":\"2011\"},{\"title\":\"2010\",\"value\":\"2010\"},{\"title\":\"2009\",\"value\":\"2009\"},{\"title\":\"2008\",\"value\":\"2008\"},{\"title\":\"2007\",\"value\":\"2007\"},{\"title\":\"2006\",\"value\":\"2006\"},{\"title\":\"2005\",\"value\":\"2005\"},{\"title\":\"2004\",\"value\":\"2004\"},{\"title\":\"2003\",\"value\":\"2003\"},{\"title\":\"2002\",\"value\":\"2002\"},{\"title\":\"2001\",\"value\":\"2001\"},{\"title\":\"2000\",\"value\":\"2000\"},{\"title\":\"1999\",\"value\":\"1999\"}],\"key\":\"year\",\"value\":\"\"},{\"items\":[{\"title\":\"全部\",\"value\":\"\"},{\"title\":\"时间\",\"value\":\"time\"},{\"title\":\"人气\",\"value\":\"hits\"},{\"title\":\"评分\",\"value\":\"score\"}],\"key\":\"sort\",\"value\":\"\"}]},{\"title\":\"Netflix美剧\",\"requestFilters\":[]},{\"title\":\"福利\",\"requestFilters\":[{\"items\":[{\"title\":\"全部\",\"value\":\"\"},{\"title\":\"时间\",\"value\":\"time\"},{\"title\":\"人气\",\"value\":\"hits\"},{\"title\":\"评分\",\"value\":\"score\"}],\"key\":\"sort\",\"value\":\"\"}]}]}","discoverNextUrl":"","discoverItems":"","discoverList":"//a[@class=\"module-poster-item module-item\"]","discoverTags":"","discoverName":"//div[@class=\"module-poster-item-title\"]/text()","discoverCover":"//div[@class=\"module-item-pic\"]/img/@data-original","discoverAuthor":"","discoverChapter":"//div[@class=\"module-item-note\"]/text()","discoverDescription":"//div[@class=\"module-item-douban\"]/text()","discoverResult":"href","enableSearch":true,"searchUrl":"/vodsearch/$keyword----------$page---.html","searchNextUrl":"","searchItems":"","searchList":"//div[@class=\"module-card-item module-item\"]","searchTags":"//div[@class=\"module-info-item\"][1]/div[1]/text()","searchName":"//div[@class=\"module-card-item-title\"]/a/strong/text()","searchCover":"//div[@class=\"module-item-pic\"]/img/@data-original","searchAuthor":"","searchChapter":"//div[@class=\"module-item-note\"]/text()","searchDescription":"//div[@class=\"module-info-item\"][2]/div[1]/text()","searchResult":"//div[@class=\"module-card-item-title\"]/a/@href","enableMultiRoads":true,"chapterRoads":"@js:\r\n(async () => {\r\n    let praseResult = [];\r\n    let Roads = await xpath(result, \"//div[contains(@class,\\\"module-tab-item tab-item\\\")]/@data-dropdown-value\");\r\n    let ChapterList = await xpath(result, \"//div[@class=\\\"module-play-list\\\"]/node()\");\r\n    print(ChapterList.length);\r\n\r\n    for (let index = 0; index < ChapterList.length; index++) {\r\n        let item_road = [];\r\n        let list = (await xpath(ChapterList[index], \"//div[contains(@class,\\\"module-play-list-content\\\")]/node()\"));\r\n        for (let j = 0; j < list.length; j++) {\r\n            let title = (await xpath(list[j], \"//a/text()\")).join('');\r\n            let url = (await xpath(list[j], \"//a/@href\")).join('');\r\n            item_road.push({\r\n                'title': title,\r\n                'url': url,\r\n            });\r\n        }\r\n        praseResult.push({\r\n            'roadName': Roads[index],\r\n            'items': item_road,\r\n        });\r\n    }\r\n    //print(JSON.stringify(praseResult));\r\n    return praseResult;\r\n})()\r\n","chapterRoadName":"$.roadName","chapterUrl":"","chapterNextUrl":"","chapterItems":"","chapterList":"$.items","chapterName":"$.title","chapterCover":"","chapterLock":"","chapterTime":"","chapterResult":"$.url","contentUrl":"","contentNextUrl":"","contentItems":"@js:lastResult@filter:(?:\\.m3u8\\?|\\.mp4|index.m3u8$|jhyun.m3u8|playlist.m3u8$|\\.m3u8$)@json:$..url@replace:.*?url=|.*?v=@js:let url = decodeURIComponent(result);if(url.startsWith(\"//\")) url = \"https:\"+ url; url.replace(\".mp4&\", \".mp4?\").replace(\".m3u8&\", \".m3u8?\")","loginUrl":"","cookies":"searchneed=ok","viewStyle":0}
